littleme/__init__.py
littleme/config.py
littleme/journal.py
littleme/llm.py
littleme/main.py
littleme/memory.py
littleme/prompts.py
littleme-0.1.dist-info/METADATA
littleme-0.1.dist-info/WHEEL
littleme-0.1.dist-info/entry_points.txt
littleme-0.1.dist-info/top_level.txt
littleme-0.1.dist-info/RECORD
