Metadata-Version: 2.4
Name: littleme
Version: 0.1
Requires-Dist: google-generativeai
Requires-Dist: rich
Requires-Dist: typer
Requires-Dist: pyfiglet
Dynamic: requires-dist
